web_screen_annotator/__init__.py
web_screen_annotator/data_annotator.py
web_screen_annotator/dom_element.py
web_screen_annotator/dom_extractor.py
web_screen_annotator/main.py
web_screen_annotator-0.1.1.dist-info/METADATA
web_screen_annotator-0.1.1.dist-info/WHEEL
web_screen_annotator-0.1.1.dist-info/top_level.txt
web_screen_annotator-0.1.1.dist-info/RECORD
