Metadata-Version: 2.1
Name: web-screen-annotator
Version: 0.1.1
Summary: data extraction library
Home-page: UNKNOWN
Author: Ghaith Nabli
License: UNKNOWN
Platform: UNKNOWN
Classifier: Intended Audience :: Developers
Classifier: License :: OSI Approved :: MIT License
Classifier: Programming Language :: Python
Classifier: Programming Language :: Python :: 3
Classifier: Programming Language :: Python :: 3.6
Classifier: Programming Language :: Python :: 3.7
Classifier: Programming Language :: Python :: 3.8
Classifier: Programming Language :: Python :: 3.9
Classifier: Operating System :: OS Independent
Requires-Dist: webdriver-manager
Requires-Dist: selenium
Requires-Dist: pillow
